{"normalForm":false,"headword":"FILIA","etymology":[{"period":"PIE ","form":"dh(e)h1i-l-","def":"suckling, child","certitude":true},{"period":"PI","form":"fīliā-","def":"daughter ","certitude":true},{"period":"It. ","form":"figlia","def":"daughter ","certitude":true},{"period":"Fr. ","form":"fille","def":"daughter ","certitude":true}],"dataFormat":"cent","meanings":[{"id":"djpakm","definition":"daughter ","construct":"_","group":"Italian figlia","emergence":10,"disparition":"None","attestation":"","relationships":{"origins":[],"destinations":[{"rel":"bwbdwxdt","cert":true}],"unspecified":[]}},{"id":"louq","definition":"daughter","construct":"_","group":"French fille","emergence":10,"disparition":"None","attestation":"","relationships":{"origins":[],"destinations":[{"rel":"jinuuhlq","cert":true}],"unspecified":[]}},{"id":"jinuuhlq","definition":"girl ","construct":"_","group":"French fille","emergence":15,"disparition":"None","attestation":"","relationships":{"origins":[{"rel":"louq","cert":true}],"destinations":[],"unspecified":[]}},{"id":"ehdotlw","definition":"daughter ","construct":"_","group":"Spanish hija","emergence":11,"disparition":"None","attestation":"","relationships":{"origins":[],"destinations":[],"unspecified":[]}},{"id":"bwbdwxdt","definition":"my dear  ","construct":"figlia (vocative)","group":"_","emergence":20,"disparition":"None","attestation":"","relationships":{"origins":[{"rel":"djpakm","cert":true}],"destinations":[],"unspecified":[]}}]}